snakemk_util/__init__.py
snakemk_util/formatting.py
snakemk_util/main.py
snakemk_util/rule_args.py
snakemk_util-2.0.0.dist-info/METADATA
snakemk_util-2.0.0.dist-info/WHEEL
snakemk_util-2.0.0.dist-info/entry_points.txt
snakemk_util-2.0.0.dist-info/top_level.txt
snakemk_util-2.0.0.dist-info/RECORD
