Metadata-Version: 2.4
Name: snakemk_util
Version: 2.0.0
Summary: utility functions for snakemake
Author-email: "Florian R. Hölzlwimmer" <git.ich@frhoelzlwimmer.de>
License-Expression: MIT
Project-URL: Homepage, https://github.com/Hoeze/snakemk_util
Requires-Python: >=3.6
Requires-Dist: snakemake<10,>=8
Provides-Extra: develop
Requires-Dist: bumpversion; extra == "develop"
Requires-Dist: wheel; extra == "develop"
Provides-Extra: test
Requires-Dist: pytest>=3.3.1; extra == "test"
Requires-Dist: pytest-xdist; extra == "test"
Requires-Dist: pytest-pep8; extra == "test"
Requires-Dist: pytest-mock; extra == "test"
Requires-Dist: pytest-cov; extra == "test"
